{"cameraMode":{"drawMode":0,"name":"Shaded","section":"Shading Mode"},"sceneLighting":true,"audioPlay":false,"sceneViewState":{"m_AlwaysRefresh":false,"showFog":true,"showSkybox":true,"showFlares":true,"showImageEffects":true,"showParticleSystems":true,"showVisualEffectGraphs":true,"m_FxEnabled":true},"in2DMode":false,"pivot":{"x":2.842132091522217,"y":5.245494365692139,"z":29.243148803710939},"rotation":{"x":0.04946427419781685,"y":-0.025170335546135904,"z":0.0012448187917470933,"w":0.9984663128852844},"size":22.373245239257814,"orthographic":false}